odoo/addons/mrp_byproduct_auto_create_lot/README.rst
odoo/addons/mrp_byproduct_auto_create_lot/__init__.py
odoo/addons/mrp_byproduct_auto_create_lot/__manifest__.py
odoo/addons/mrp_byproduct_auto_create_lot/i18n/es.po
odoo/addons/mrp_byproduct_auto_create_lot/i18n/it.po
odoo/addons/mrp_byproduct_auto_create_lot/i18n/mrp_byproduct_auto_create_lot.pot
odoo/addons/mrp_byproduct_auto_create_lot/i18n/nl.po
odoo/addons/mrp_byproduct_auto_create_lot/i18n/zh_CN.po
odoo/addons/mrp_byproduct_auto_create_lot/models/__init__.py
odoo/addons/mrp_byproduct_auto_create_lot/models/mrp_production.py
odoo/addons/mrp_byproduct_auto_create_lot/readme/CONFIGURE.md
odoo/addons/mrp_byproduct_auto_create_lot/readme/CONTRIBUTORS.md
odoo/addons/mrp_byproduct_auto_create_lot/readme/DESCRIPTION.md
odoo/addons/mrp_byproduct_auto_create_lot/readme/USAGE.md
odoo/addons/mrp_byproduct_auto_create_lot/static/description/icon.png
odoo/addons/mrp_byproduct_auto_create_lot/static/description/index.html
odoo/addons/mrp_byproduct_auto_create_lot/tests/__init__.py
odoo/addons/mrp_byproduct_auto_create_lot/tests/common.py
odoo/addons/mrp_byproduct_auto_create_lot/tests/test_mrp_byproduct_auto_create_lot.py
odoo_addon_mrp_byproduct_auto_create_lot-18.0.1.0.0.2.dist-info/METADATA
odoo_addon_mrp_byproduct_auto_create_lot-18.0.1.0.0.2.dist-info/WHEEL
odoo_addon_mrp_byproduct_auto_create_lot-18.0.1.0.0.2.dist-info/top_level.txt
odoo_addon_mrp_byproduct_auto_create_lot-18.0.1.0.0.2.dist-info/RECORD
